ledgercommon/__init__.py
ledgercommon/setup.py
python_ledgercommon-1.56.10.dist-info/METADATA
python_ledgercommon-1.56.10.dist-info/WHEEL
python_ledgercommon-1.56.10.dist-info/top_level.txt
python_ledgercommon-1.56.10.dist-info/RECORD
