Metadata-Version: 2.4
Name: python-ledgercommon
Version: 1.56.10
Summary: Ledger common utilities
Author-email: Ledger Donjon <donjon@ledger.fr>
Requires-Python: <3.14,>=3.10
